FinalData/__init__.py
FinalData-0.0.1.dist-info/LICENSE.txt
FinalData-0.0.1.dist-info/METADATA
FinalData-0.0.1.dist-info/WHEEL
FinalData-0.0.1.dist-info/top_level.txt
FinalData-0.0.1.dist-info/RECORD
