Metadata-Version: 2.1
Name: FinalData
Version: 0.0.1
Summary: This module contains total 3 functions for EDA operations, doing balancing of unbalanced data, train_test split and finally getting profile report of raw initial and final refined data & saving them in as html file
Home-page: https://github.com/sachiniitdelhi2021/Published-python-module-2----FinalData
Author: Sachin Dangi
Author-email: sachiniit36@gmail.com
License: UNKNOWN
Keywords: data,Data,FinalData,finalData,finaldata
Platform: UNKNOWN
Classifier: Programming Language :: Python :: 3
Classifier: License :: OSI Approved :: MIT License
Classifier: Operating System :: OS Independent
Requires-Python: >=3.6
License-File: LICENSE.txt
